electron_fuses/__init__.py
electron_fuses/config.py
electron_fuses/resolve.py
electron_fuses/resources.py
electron_fuses/version.py
electron_fuses-1.4.0.dist-info/LICENSE.txt
electron_fuses-1.4.0.dist-info/METADATA
electron_fuses-1.4.0.dist-info/WHEEL
electron_fuses-1.4.0.dist-info/top_level.txt
electron_fuses-1.4.0.dist-info/RECORD
