Metadata-Version: 2.1
Name: electron_fuses
Version: 1.4.0
Summary: Python-implementation of Electron's fuses module.
Home-page: https://github.com/ripeda/Electron-Fuses
Author: RIPEDA Consulting
Author-email: info@ripeda.com
License: 3-clause BSD License
Requires-Python: >=3.6
License-File: LICENSE.txt
Requires-Dist: requests
Requires-Dist: bs4
